soilapis/__init__.py
soilapis/calculator.py
soilapis/extract_country_bbox.py
soilapis/fortran_apis.py
soilapis/summary_soil_property.py
soilapis-0.0.1.dist-info/LICENSE.txt
soilapis-0.0.1.dist-info/METADATA
soilapis-0.0.1.dist-info/WHEEL
soilapis-0.0.1.dist-info/top_level.txt
soilapis-0.0.1.dist-info/RECORD
